pattern_flow/__init__.py
pattern_flow/main.py
pattern_flow/mainView.py
pattern_flow/export/__init__.py
pattern_flow/export/localFile.py
pattern_flow/load/__init__.py
pattern_flow/load/camera.py
pattern_flow/load/file.py
pattern_flow/processer/__init__.py
pattern_flow/processer/bilateralFilter.py
pattern_flow/processer/cannyLine.py
pattern_flow/processer/conditionBGR.py
pattern_flow/processer/contourPoint.py
pattern_flow/processer/gussBlur.py
pattern_flow/processer/otsuSplit.py
pattern_flow/processer/reconginizeFace.py
pattern_flow/processer/traceColor.py
pattern_flow/processer/common/__init__.py
pattern_flow/processer/common/base.py
pattern_flow/processer/common/parameter.py
pattern_flow/util/__init__.py
pattern_flow/util/image.py
pattern_flow/util/thread.py
pattern_flow-0.0.1.dist-info/LICENSE
pattern_flow-0.0.1.dist-info/METADATA
pattern_flow-0.0.1.dist-info/WHEEL
pattern_flow-0.0.1.dist-info/top_level.txt
pattern_flow-0.0.1.dist-info/RECORD
